signed_multiplication_using_booth_algorithm/signed_multiplication_using_booth_algorithm.srcs/sources_1/new/controlpath.v
`timescale 1ns / 1ps
//////////////////////////////////////////////////////////////////////////////////
// Company: 
// Engineer: 
// 
// Create Date: 07/29/2021 11:53:20 AM
// Design Name: 
// Module Name: controlpath
// Project Name: 
// Target Devices: 
// Tool Versions: 
// Description: 
// 
// Dependencies: 
// 
// Revision:
// Revision 0.01 - File Created
// Additional Comments:
// 
//////////////////////////////////////////////////////////////////////////////////
module shiftrg ( output reg [7:0] a,
              input [7:0] b,
              input lda,clr,r,clk,g
             );
             always @( posedge clk)
               if(clr)
                 a = 8'b00000000;
               else if(lda)
                  a <=b;
               else if(r)
                  a ={g,a[7:1]};
endmodule
module shiftrg1 ( output reg [7:0] a,
              input [7:0] b,
              input lda,r,clk,g
             );
             always @( posedge clk)
               //if(clr)
                 //a = 4'b0000;
               if(lda)
                  a <=b;
               
               else if(r)
                  a ={g,a[7:1]};
endmodule
module pipo1 ( output reg [7:0] a,
              input [7:0] b,
              input ldq,clk
             );
             always @(posedge clk)
                if(ldq)
                  a <= b;       
endmodule
module alu (output reg [7:0] a,
              input [7:0] b,c,
              input ac,m
              );
              always @(*)
                 if(ac==1 && m==1)
                   a = b - c;
                 else if(ac == 1 && m ==0)
                   a = b+c;
endmodule
//module rshift (output reg [3:0] a,b,
  //             
    //           output reg q,
      //         input [3:0] e,d,
        //       input r,clk
          //     );
            //   reg c;
              // initial begin
//              a = e;
  //             b = d; end
    //           always @( posedge clk)begin
      //         q = d[0];//9783504088
        //         if(r)
          ///         begin
             //       c = d[0];
               //    a = d>>1;
                 //  b = e>>1;
                   // b[3] = c;
                    //end
                 //end   
//endmodule
module counter(output reg [3:0] dec,
               input s,clk,r
               );
              always @(posedge clk)
               if(s)
                dec <= 4'b1000;
               else if(r)
                 dec = dec-4'b0001;
endmodule
module regs(output reg q1,
            input a,clr,clk,r
            );
            always @(posedge clk)
              if(clr)
               q1 = 1'b0;
              else if(r)
                q1 = a;
endmodule               
module datapath( output q,q1,dc,
                 output [15:0] z,
                 input ldm,ldq,lda,rs,ac,t,clk,clra,
                 input [7:0] data_in
                 );
                 wire [7:0] d,a,qo,m;
                 wire [3:0] k;
           //   pipo A (a,d,lda,clk,clra);
            //  pipo1 Q (qo,bus,ldq,clk);
              pipo1 M (m,data_in,ldm,clk);
              alu A1 (d,a,m,ac,t); 
              shiftrg A (a,d,lda,clra,rs,clk,a[3]);
              shiftrg1 Q (qo,data_in,ldq,rs,clk,a[0]);
              counter DC(k,clra,clk,rs);
              regs R (q1,qo[0],clra,clk,rs);
              assign z = {a,qo},
                     q = qo[0],
                     dc = (k==0);
endmodule   
module controlpath( output reg ldm,ldq,lda,rs,ac,t,clra,done,
                    input  q,q1,dc,clk,start
                    );
                    parameter s0 = 3'b000, s1 = 3'b001, s2 = 3'b010, s3 = 3'b011, s4 = 3'b100, s5 = 3'b101;
                    reg [2:0] state;
                    always @(state)
                      begin
                         case(state)
                             s0: begin
                                   ldm =1'b0; 
                                   ldq = 1'b1;
                                   lda = 1'b0;
                                   rs = 1'b0;
                                   ac = 1'b0;
                                   clra = 1'b0;
                                   done =0;
                                  end
                             s1: begin
                                  ldq = 1'b0;
                                   ldm =1'b1;
                                   clra = 1'b1;
                                 end
                             s2: begin
                                   ldm = 1'b0;
                                   clra = 1'b0;
                                   ldq = 0;
                                   ac = 0;
                                  // rs =0;
                                   lda = 0;
                                  if(dc)
                                  begin   done = 1'b1;end
                                 // else if(q)
                                //  begin
                                //     ad = 1'b1;
                                 //    #2 lda = 1'b1;
                               //      #2 rs= 1'b1; end
                              //    else if(!q)
                                   rs = 1'b1;
                                    
                                  end
                             s3: begin
                                  ldm = 1'b0;
                                  clra = 1'b0;
                                  ldq = 0;
                                  rs = 0;
                                  ac = 1;
                                  t = 0;
                                 #2 lda = 1;
                                  
                                  
                                  // lda <= 1'b1;
                                   //r <= 1'b1;
                                   if(dc==1)
                                   begin  done = 1;end
                                 //  else if(q)
                                   //  begin
                                     //  ad = 1;
                                       //#2 lda = 1;
                                       //#2 rs = 1;
                                       //end
                                   //else if(!q)
                                     //  rs = 1;
                                       
                                       
                                 end
                             s4: begin
                                 ldm =0;
                                 clra =0;
                                 rs =0;
                                 ac=1;
                                 t=1;
                                 #2 lda=1;
                                 end
                             s5: begin
                                   ldm =1'b0; 
                                                                                                 ldq = 1'b0;
                                                                                                 lda = 1'b0;
                                                                                                 rs = 1'b0;
                                                                                                 ac = 1'b0;
                                                                                                 clra = 1'b0;
                                                                                                 done =1;
                                                                                                 t=0;
                                                                                                 
                                 end
                            default: begin
                                                                    ldm =1'b0; 
                                                                    ldq = 1'b1;
                                                                    lda = 1'b0;
                                                                    rs = 1'b0;
                                                                    ac = 1'b0;
                                                                    clra = 1'b0;
                                                                    done =0;
                                                                   end
                        endcase
                     end
        always @(posedge clk)
          begin
            case(state)
               s0:begin if(start) state = s1;end
              // s1: state = s2;
               s1: begin
                     if({q,q1}==2'b01)
                       state = s3;
                     else if({q,q1} == 2'b10)
                       state = s4;
                     else
                       state = s2;
                   end
               s2: begin 
                    if(dc)
                       state = s5;
                    else if({q,q1} ==2'b01)
                       state = s3;
                     else if({q,q1} == 2'b10)
                        state = s4;
                    // else if(!q)
                    //     state = s2;
                    end
               s3: begin
                    // if(q)
                     //  state = s2;
                     if(dc)
                       state = s5;
                     else 
                        state = s2;
                   //  else if(!q)
                     //   state = s2;
                    end 
               s4:begin
                     if(dc)
                       state = s5;
                     else
                       state = s2;
                     end
               s5: state =s5;
               default: state = s0;
            endcase
          end               
endmodule

signed_multiplication_using_booth_algorithm/signed_multiplication_using_booth_algorithm.srcs/sim_1/new/bsm_test.v
`timescale 1ns / 1ps
//////////////////////////////////////////////////////////////////////////////////
// Company: 
// Engineer: 
// 
// Create Date: 07/29/2021 12:26:38 PM
// Design Name: 
// Module Name: bsm_test
// Project Name: 
// Target Devices: 
// Tool Versions: 
// Description: 
// 
// Dependencies: 
// 
// Revision:
// Revision 0.01 - File Created
// Additional Comments:
// 
//////////////////////////////////////////////////////////////////////////////////

//problab is overflow
module bsm_test();
wire done; 
wire [15:0] z;
reg [7:0] data_in; 
reg clk,start;
datapath DP (q,q1,dc,z,ldm,ldq,lda,rs,ac,t,clk,clra,data_in); 
controlpath CON(ldm,ldq,lda,rs,ac,t,clra,done,q,q1,dc,clk,start); 
//bm DUT(.z(z),.clk(clk),.clr(clr),.a(a),.b(b));
initial 
begin 
clk = 1'b0; 
#3start = 1'b1;
//#8 clr = 1'b1; 
#1000 $finish; 
end 
always #5 clk = ~clk;
initial 
 begin 
 #10data_in = 8'b00000101; 
 #12 data_in =8'b11111010; 
 end 
 initial
 begin 
 $monitor ($time, " %d %b %b %b %b %b %b", z,DP.a,DP.qo,DP.m,DP.q,DP.q1,done); 
$dumpfile ("bsm.vcd"); $dumpvars (0, bsm_test); 
 end 
endmodule

signed_multiplication_using_booth_algorithm/signed_multiplication_using_booth_algorithm.sim/sim_1/behav/bsm.vcd
$date
   Tue Aug 23 20:08:27 2022
$end
$version
  13.1
$end
$timescale
  1ps
$end
$scope module bsm_test $end
$var wire 1 ! done $end
$var wire 16 " z [15:0] $end
$var reg 8 # data_in [7:0] $end
$var reg 1 $ clk $end
$var reg 1 % start $end
$var wire 1 & q $end
$var wire 1 ' q1 $end
$var wire 1 ( dc $end
$var wire 1 ) ldm $end
$var wire 1 * ldq $end
$var wire 1 + lda $end
$var wire 1 , rs $end
$var wire 1 - ac $end
$var wire 1 . t $end
$var wire 1 / clra $end
$scope module DP $end
$var wire 1 0 q $end
$var wire 1 1 q1 $end
$var wire 1 2 dc $end
$var wire 16 3 z [15:0] $end
$var wire 1 4 ldm $end
$var wire 1 5 ldq $end
$var wire 1 6 lda $end
$var wire 1 7 rs $end
$var wire 1 8 ac $end
$var wire 1 9 t $end
$var wire 1 : clk $end
$var wire 1 ; clra $end
$var wire 8 < data_in [7:0] $end
$var wire 8 = d [7:0] $end
$var wire 8 > a [7:0] $end
$var wire 8 ? qo [7:0] $end
$var wire 8 @ m [7:0] $end
$var wire 4 A k [3:0] $end
$scope module M $end
$var reg 8 B a [7:0] $end
$var wire 8 C b [7:0] $end
$var wire 1 D ldq $end
$var wire 1 E clk $end
$upscope $end
$scope module A1 $end
$var reg 8 F a [7:0] $end
$var wire 8 G b [7:0] $end
$var wire 8 H c [7:0] $end
$var wire 1 I ac $end
$var wire 1 J m $end
$upscope $end
$scope module A $end
$var reg 8 K a [7:0] $end
$var wire 8 L b [7:0] $end
$var wire 1 M lda $end
$var wire 1 N clr $end
$var wire 1 O r $end
$var wire 1 P clk $end
$var wire 1 Q g $end
$upscope $end
$scope module Q $end
$var reg 8 R a [7:0] $end
$var wire 8 S b [7:0] $end
$var wire 1 T lda $end
$var wire 1 U r $end
$var wire 1 V clk $end
$var wire 1 W g $end
$upscope $end
$scope module DC $end
$var reg 4 X dec [3:0] $end
$var wire 1 Y s $end
$var wire 1 Z clk $end
$var wire 1 [ r $end
$upscope $end
$scope module R $end
$var reg 1 \ q1 $end
$var wire 1 ] a $end
$var wire 1 ^ clr $end
$var wire 1 _ clk $end
$var wire 1 ` r $end
$upscope $end
$upscope $end
$scope module CON $end
$var reg 1 a ldm $end
$var reg 1 b ldq $end
$var reg 1 c lda $end
$var reg 1 d rs $end
$var reg 1 e ac $end
$var reg 1 f t $end
$var reg 1 g clra $end
$var reg 1 h done $end
$var wire 1 i q $end
$var wire 1 j q1 $end
$var wire 1 k dc $end
$var wire 1 l clk $end
$var wire 1 m start $end
$var reg 3 n state [2:0] $end
$var parameter 3 o s0 [2:0] $end
$var parameter 3 p s1 [2:0] $end
$var parameter 3 q s2 [2:0] $end
$var parameter 3 r s3 [2:0] $end
$var parameter 3 s s4 [2:0] $end
$var parameter 3 t s5 [2:0] $end
$upscope $end
$upscope $end
$enddefinitions $end
#0
$dumpvars
x!
bx "
bx #
0$
x%
x&
x'
x(
x)
x*
x+
x,
x-
x.
x/
x0
x1
x2
bx 3
x4
x5
x6
x7
x8
x9
0:
x;
bx <
bx =
bx >
bx ?
bx @
bx A
bx B
bx C
xD
0E
bx F
bx G
bx H
xI
xJ
bx K
bx L
xM
xN
xO
0P
xQ
bx R
bx S
xT
xU
0V
xW
bx X
xY
0Z
x[
x\
x]
x^
0_
x`
xa
xb
xc
xd
xe
xf
xg
xh
xi
xj
xk
0l
xm
bx n
b0 o
b1 p
b10 q
b11 r
b100 s
b101 t
$end
#3000
1%
1m
#5000
0!
1$
0)
1*
0+
0,
0-
0/
04
15
06
07
08
1:
0;
0D
1E
0I
0M
0N
0O
1P
1T
0U
1V
0Y
1Z
0[
0^
1_
0`
0a
1b
0c
0d
0e
0g
0h
1l
b0 n
#10000
b101 #
0$
0:
b101 <
b101 C
0E
0P
b101 S
0V
0Z
0_
0l
#15000
bx00000101 "
1$
1&
1)
0*
1/
10
bx00000101 3
14
05
1:
1;
b101 ?
1D
1E
1N
1P
b101 R
0T
1V
1Y
1Z
1]
1^
1_
1a
0b
1g
1i
1l
b1 n
#20000
0$
0:
0E
0P
0V
0Z
0_
0l
#22000
b11111010 #
b11111010 <
b11111010 C
b11111010 S
#25000
b101 "
1$
0'
0(
0)
1,
0/
01
02
b101 3
04
17
1:
0;
b0 >
b11111010 @
b1000 A
b11111010 B
0D
1E
b0 G
b11111010 H
b0 K
0N
1O
1P
1U
1V
0W
b1000 X
0Y
1Z
1[
0\
0^
1_
1`
0a
0b
0c
1d
0e
0g
0j
0k
1l
b10 n
#30000
0$
0:
0E
0P
0V
0Z
0_
0l
#35000
b10 "
1$
0&
1'
0,
1-
1.
00
11
b10 3
07
18
19
1:
b110 =
b10 ?
b111 A
1E
b110 F
1I
1J
b0 K
b110 L
0O
1P
b10 R
0U
1V
b111 X
1Z
0[
1\
0]
1_
0`
0a
0d
1e
1f
0g
0i
1j
1l
b100 n
#37000
1+
16
1M
1c
#40000
0$
0:
0E
0P
0V
0Z
0_
0l
#45000
b11000000010 "
1$
0+
1,
0-
b11000000010 3
06
17
08
1:
b110 >
1E
b110 G
0I
b110 K
0M
1O
1P
1U
1V
0W
1Z
1[
1_
1`
0a
0b
0c
1d
0e
0g
1l
b10 n
#50000
0$
0:
0E
0P
0V
0Z
0_
0l
#55000
b1100000001 "
1$
1&
0'
0,
1-
0.
10
01
b1100000001 3
07
18
09
1:
b11111101 =
b11 >
b1 ?
b110 A
1E
b11111101 F
b11 G
1I
0J
b11 K
b11111101 L
0O
1P
b1 R
0U
1V
1W
b110 X
1Z
0[
0\
1]
1_
0`
0a
0b
0d
1e
0f
0g
1i
0j
1l
b11 n
#57000
1+
16
1M
1c
#60000
0$
0:
0E
0P
0V
0Z
0_
0l
#65000
b1111110100000001 "
1$
0+
1,
0-
b1111110100000001 3
06
17
08
1:
b11111101 >
1E
b11111101 G
0I
b11111101 K
0M
1O
1P
1U
1V
1W
1Z
1[
1_
1`
0a
0b
0c
1d
0e
0g
1l
b10 n
#70000
0$
0:
0E
0P
0V
0Z
0_
0l
#75000
b1111111010000000 "
1$
0&
1'
0,
1-
1.
00
11
b1111111010000000 3
07
18
19
1:
b100 =
b11111110 >
b10000000 ?
b101 A
1E
b100 F
b11111110 G
1I
1J
b11111110 K
b100 L
0O
1P
b10000000 R
0U
1V
0W
b101 X
1Z
0[
1\
0]
1_
0`
0a
0d
1e
1f
0g
0i
1j
1l
b100 n
#77000
1+
16
1M
1c
#80000
0$
0:
0E
0P
0V
0Z
0_
0l
#85000
b10010000000 "
1$
0+
1,
0-
b10010000000 3
06
17
08
1:
b100 >
1E
b100 G
0I
b100 K
0M
1O
1P
1U
1V
0W
1Z
1[
1_
1`
0a
0b
0c
1d
0e
0g
1l
b10 n
#90000
0$
0:
0E
0P
0V
0Z
0_
0l
#95000
b1001000000 "
1$
0'
0,
1-
0.
01
b1001000000 3
07
18
09
1:
b11111100 =
b10 >
b1000000 ?
b100 A
1E
b11111100 F
b10 G
1I
0J
b10 K
b11111100 L
0O
1P
b1000000 R
0U
1V
0W
b100 X
1Z
0[
0\
0]
1_
0`
0a
0b
0d
1e
0f
0g
0j
1l
b11 n
#97000
1+
16
1M
1c
#100000
0$
0:
0E
0P
0V
0Z
0_
0l
#105000
b1111110001000000 "
1$
0+
1,
0-
b1111110001000000 3
06
17
08
1:
b11111100 >
1E
b11111100 G
0I
b11111100 K
0M
1O
1P
1U
1V
0W
1Z
1[
1_
1`
0a
0b
0c
1d
0e
0g
1l
b10 n
#110000
0$
0:
0E
0P
0V
0Z
0_
0l
#115000
b1111111000100000 "
1$
b1111111000100000 3
1:
b11111110 >
b100000 ?
b11 A
1E
b11111110 G
b11111110 K
1P
b100000 R
1V
0W
b11 X
1Z
0\
0]
1_
1l
#120000
0$
0:
0E
0P
0V
0Z
0_
0l
#125000
b1111111100010000 "
1$
b1111111100010000 3
1:
b11111111 >
b10000 ?
b10 A
1E
b11111111 G
b11111111 K
1P
b10000 R
1V
1W
b10 X
1Z
0\
0]
1_
1l
#130000
0$
0:
0E
0P
0V
0Z
0_
0l
#135000
b1111111110001000 "
1$
b1111111110001000 3
1:
b10001000 ?
b1 A
1E
b11111111 K
1P
b10001000 R
1V
b1 X
1Z
0\
0]
1_
1l
#140000
0$
0:
0E
0P
0V
0Z
0_
0l
#145000
b1111111111000100 "
1$
1(
12
b1111111111000100 3
1:
b11000100 ?
b0 A
1E
b11111111 K
1P
b11000100 R
1V
b0 X
1Z
0\
0]
1_
1k
1l
#150000
0$
0:
0E
0P
0V
0Z
0_
0l
#155000
1!
b1111111111100010 "
1$
0(
0,
02
b1111111111100010 3
07
1:
b11100010 ?
b1111 A
1E
b11111111 K
0O
1P
b11100010 R
0U
1V
b1111 X
1Z
0[
0\
0]
1_
0`
0a
0b
0c
0d
0e
0f
0g
1h
0k
1l
b101 n
#160000
0$
0:
0E
0P
0V
0Z
0_
0l
#165000
1$
1:
1E
1P
1V
1Z
1_
1l
b101 n
#170000
0$
0:
0E
0P
0V
0Z
0_
0l
#175000
1$
1:
1E
1P
1V
1Z
1_
1l
b101 n
#180000
0$
0:
0E
0P
0V
0Z
0_
0l
#185000
1$
1:
1E
1P
1V
1Z
1_
1l
b101 n
#190000
0$
0:
0E
0P
0V
0Z
0_
0l
#195000
1$
1:
1E
1P
1V
1Z
1_
1l
b101 n
#200000
0$
0:
0E
0P
0V
0Z
0_
0l
#205000
1$
1:
1E
1P
1V
1Z
1_
1l
b101 n
#210000
0$
0:
0E
0P
0V
0Z
0_
0l
#215000
1$
1:
1E
1P
1V
1Z
1_
1l
b101 n
#220000
0$
0:
0E
0P
0V
0Z
0_
0l
#225000
1$
1:
1E
1P
1V
1Z
1_
1l
b101 n
#230000
0$
0:
0E
0P
0V
0Z
0_
0l
#235000
1$
1:
1E
1P
1V
1Z
1_
1l
b101 n
#240000
0$
0:
0E
0P
0V
0Z
0_
0l
#245000
1$
1:
1E
1P
1V
1Z
1_
1l
b101 n
#250000
0$
0:
0E
0P
0V
0Z
0_
0l
#255000
1$
1:
1E
1P
1V
1Z
1_
1l
b101 n
#260000
0$
0:
0E
0P
0V
0Z
0_
0l
#265000
1$
1:
1E
1P
1V
1Z
1_
1l
b101 n
#270000
0$
0:
0E
0P
0V
0Z
0_
0l
#275000
1$
1:
1E
1P
1V
1Z
1_
1l
b101 n
#280000
0$
0:
0E
0P
0V
0Z
0_
0l
#285000
1$
1:
1E
1P
1V
1Z
1_
1l
b101 n
#290000
0$
0:
0E
0P
0V
0Z
0_
0l
#295000
1$
1:
1E
1P
1V
1Z
1_
1l
b101 n
#300000
0$
0:
0E
0P
0V
0Z
0_
0l
#305000
1$
1:
1E
1P
1V
1Z
1_
1l
b101 n
#310000
0$
0:
0E
0P
0V
0Z
0_
0l
#315000
1$
1:
1E
1P
1V
1Z
1_
1l
b101 n
#320000
0$
0:
0E
0P
0V
0Z
0_
0l
#325000
1$
1:
1E
1P
1V
1Z
1_
1l
b101 n
#330000
0$
0:
0E
0P
0V
0Z
0_
0l
#335000
1$
1:
1E
1P
1V
1Z
1_
1l
b101 n
#340000
0$
0:
0E
0P
0V
0Z
0_
0l
#345000
1$
1:
1E
1P
1V
1Z
1_
1l
b101 n
#350000
0$
0:
0E
0P
0V
0Z
0_
0l
#355000
1$
1:
1E
1P
1V
1Z
1_
1l
b101 n
#360000
0$
0:
0E
0P
0V
0Z
0_
0l
#365000
1$
1:
1E
1P
1V
1Z
1_
1l
b101 n
#370000
0$
0:
0E
0P
0V
0Z
0_
0l
#375000
1$
1:
1E
1P
1V
1Z
1_
1l
b101 n
#380000
0$
0:
0E
0P
0V
0Z
0_
0l
#385000
1$
1:
1E
1P
1V
1Z
1_
1l
b101 n
#390000
0$
0:
0E
0P
0V
0Z
0_
0l
#395000
1$
1:
1E
1P
1V
1Z
1_
1l
b101 n
#400000
0$
0:
0E
0P
0V
0Z
0_
0l
#405000
1$
1:
1E
1P
1V
1Z
1_
1l
b101 n
#410000
0$
0:
0E
0P
0V
0Z
0_
0l
#415000
1$
1:
1E
1P
1V
1Z
1_
1l
b101 n
#420000
0$
0:
0E
0P
0V
0Z
0_
0l
#425000
1$
1:
1E
1P
1V
1Z
1_
1l
b101 n
#430000
0$
0:
0E
0P
0V
0Z
0_
0l
#435000
1$
1:
1E
1P
1V
1Z
1_
1l
b101 n
#440000
0$
0:
0E
0P
0V
0Z
0_
0l
#445000
1$
1:
1E
1P
1V
1Z
1_
1l
b101 n
#450000
0$
0:
0E
0P
0V
0Z
0_
0l
#455000
1$
1:
1E
1P
1V
1Z
1_
1l
b101 n
#460000
0$
0:
0E
0P
0V
0Z
0_
0l
#465000
1$
1:
1E
1P
1V
1Z
1_
1l
b101 n
#470000
0$
0:
0E
0P
0V
0Z
0_
0l
#475000
1$
1:
1E
1P
1V
1Z
1_
1l
b101 n
#480000
0$
0:
0E
0P
0V
0Z
0_
0l
#485000
1$
1:
1E
1P
1V
1Z
1_
1l
b101 n
#490000
0$
0:
0E
0P
0V
0Z
0_
0l
#495000
1$
1:
1E
1P
1V
1Z
1_
1l
b101 n
#500000
0$
0:
0E
0P
0V
0Z
0_
0l
#505000
1$
1:
1E
1P
1V
1Z
1_
1l
b101 n
#510000
0$
0:
0E
0P
0V
0Z
0_
0l
#515000
1$
1:
1E
1P
1V
1Z
1_
1l
b101 n
#520000
0$
0:
0E
0P
0V
0Z
0_
0l
#525000
1$
1:
1E
1P
1V
1Z
1_
1l
b101 n
#530000
0$
0:
0E
0P
0V
0Z
0_
0l
#535000
1$
1:
1E
1P
1V
1Z
1_
1l
b101 n
#540000
0$
0:
0E
0P
0V
0Z
0_
0l
#545000
1$
1:
1E
1P
1V
1Z
1_
1l
b101 n
#550000
0$
0:
0E
0P
0V
0Z
0_
0l
#555000
1$
1:
1E
1P
1V
1Z
1_
1l
b101 n
#560000
0$
0:
0E
0P
0V
0Z
0_
0l
#565000
1$
1:
1E
1P
1V
1Z
1_
1l
b101 n
#570000
0$
0:
0E
0P
0V
0Z
0_
0l
#575000
1$
1:
1E
1P
1V
1Z
1_
1l
b101 n
#580000
0$
0:
0E
0P
0V
0Z
0_
0l
#585000
1$
1:
1E
1P
1V
1Z
1_
1l
b101 n
#590000
0$
0:
0E
0P
0V
0Z
0_
0l
#595000
1$
1:
1E
1P
1V
1Z
1_
1l
b101 n
#600000
0$
0:
0E
0P
0V
0Z
0_
0l
#605000
1$
1:
1E
1P
1V
1Z
1_
1l
b101 n
#610000
0$
0:
0E
0P
0V
0Z
0_
0l
#615000
1$
1:
1E
1P
1V
1Z
1_
1l
b101 n
#620000
0$
0:
0E
0P
0V
0Z
0_
0l
#625000
1$
1:
1E
1P
1V
1Z
1_
1l
b101 n
#630000
0$
0:
0E
0P
0V
0Z
0_
0l
#635000
1$
1:
1E
1P
1V
1Z
1_
1l
b101 n
#640000
0$
0:
0E
0P
0V
0Z
0_
0l
#645000
1$
1:
1E
1P
1V
1Z
1_
1l
b101 n
#650000
0$
0:
0E
0P
0V
0Z
0_
0l
#655000
1$
1:
1E
1P
1V
1Z
1_
1l
b101 n
#660000
0$
0:
0E
0P
0V
0Z
0_
0l
#665000
1$
1:
1E
1P
1V
1Z
1_
1l
b101 n
#670000
0$
0:
0E
0P
0V
0Z
0_
0l
#675000
1$
1:
1E
1P
1V
1Z
1_
1l
b101 n
#680000
0$
0:
0E
0P
0V
0Z
0_
0l
#685000
1$
1:
1E
1P
1V
1Z
1_
1l
b101 n
#690000
0$
0:
0E
0P
0V
0Z
0_
0l
#695000
1$
1:
1E
1P
1V
1Z
1_
1l
b101 n
#700000
0$
0:
0E
0P
0V
0Z
0_
0l
#705000
1$
1:
1E
1P
1V
1Z
1_
1l
b101 n
#710000
0$
0:
0E
0P
0V
0Z
0_
0l
#715000
1$
1:
1E
1P
1V
1Z
1_
1l
b101 n
#720000
0$
0:
0E
0P
0V
0Z
0_
0l
#725000
1$
1:
1E
1P
1V
1Z
1_
1l
b101 n
#730000
0$
0:
0E
0P
0V
0Z
0_
0l
#735000
1$
1:
1E
1P
1V
1Z
1_
1l
b101 n
#740000
0$
0:
0E
0P
0V
0Z
0_
0l
#745000
1$
1:
1E
1P
1V
1Z
1_
1l
b101 n
#750000
0$
0:
0E
0P
0V
0Z
0_
0l
#755000
1$
1:
1E
1P
1V
1Z
1_
1l
b101 n
#760000
0$
0:
0E
0P
0V
0Z
0_
0l
#765000
1$
1:
1E
1P
1V
1Z
1_
1l
b101 n
#770000
0$
0:
0E
0P
0V
0Z
0_
0l
#775000
1$
1:
1E
1P
1V
1Z
1_
1l
b101 n
#780000
0$
0:
0E
0P
0V
0Z
0_
0l
#785000
1$
1:
1E
1P
1V
1Z
1_
1l
b101 n
#790000
0$
0:
0E
0P
0V
0Z
0_
0l
#795000
1$
1:
1E
1P
1V
1Z
1_
1l
b101 n
#800000
0$
0:
0E
0P
0V
0Z
0_
0l
#805000
1$
1:
1E
1P
1V
1Z
1_
1l
b101 n
#810000
0$
0:
0E
0P
0V
0Z
0_
0l
#815000
1$
1:
1E
1P
1V
1Z
1_
1l
b101 n
#820000
0$
0:
0E
0P
0V
0Z
0_
0l
#825000
1$
1:
1E
1P
1V
1Z
1_
1l
b101 n
#830000
0$
0:
0E
0P
0V
0Z
0_
0l
#835000
1$
1:
1E
1P
1V
1Z
1_
1l
b101 n
#840000
0$
0:
0E
0P
0V
0Z
0_
0l
#845000
1$
1:
1E
1P
1V
1Z
1_
1l
b101 n
#850000
0$
0:
0E
0P
0V
0Z
0_
0l
#855000
1$
1:
1E
1P
1V
1Z
1_
1l
b101 n
#860000
0$
0:
0E
0P
0V
0Z
0_
0l
#865000
1$
1:
1E
1P
1V
1Z
1_
1l
b101 n
#870000
0$
0:
0E
0P
0V
0Z
0_
0l
#875000
1$
1:
1E
1P
1V
1Z
1_
1l
b101 n
#880000
0$
0:
0E
0P
0V
0Z
0_
0l
#885000
1$
1:
1E
1P
1V
1Z
1_
1l
b101 n
#890000
0$
0:
0E
0P
0V
0Z
0_
0l
#895000
1$
1:
1E
1P
1V
1Z
1_
1l
b101 n
#900000
0$
0:
0E
0P
0V
0Z
0_
0l
#905000
1$
1:
1E
1P
1V
1Z
1_
1l
b101 n
#910000
0$
0:
0E
0P
0V
0Z
0_
0l
#915000
1$
1:
1E
1P
1V
1Z
1_
1l
b101 n
#920000
0$
0:
0E
0P
0V
0Z
0_
0l
#925000
1$
1:
1E
1P
1V
1Z
1_
1l
b101 n
#930000
0$
0:
0E
0P
0V
0Z
0_
0l
#935000
1$
1:
1E
1P
1V
1Z
1_
1l
b101 n
#940000
0$
0:
0E
0P
0V
0Z
0_
0l
#945000
1$
1:
1E
1P
1V
1Z
1_
1l
b101 n
#950000
0$
0:
0E
0P
0V
0Z
0_
0l
#955000
1$
1:
1E
1P
1V
1Z
1_
1l
b101 n
#960000
0$
0:
0E
0P
0V
0Z
0_
0l
#965000
1$
1:
1E
1P
1V
1Z
1_
1l
b101 n
#970000
0$
0:
0E
0P
0V
0Z
0_
0l
#975000
1$
1:
1E
1P
1V
1Z
1_
1l
b101 n
#980000
0$
0:
0E
0P
0V
0Z
0_
0l
#985000
1$
1:
1E
1P
1V
1Z
1_
1l
b101 n
#990000
0$
0:
0E
0P
0V
0Z
0_
0l
#995000
1$
1:
1E
1P
1V
1Z
1_
1l
b101 n
